iwin_cli/__init__.py
iwin_cli/__main__.py
iwin_cli/classconfig.py
iwin_cli/simulation.py
iwin_cli/utils.py
iwin_cli/zip.py
iwin_cli-1.0.3.dist-info/METADATA
iwin_cli-1.0.3.dist-info/WHEEL
iwin_cli-1.0.3.dist-info/entry_points.txt
iwin_cli-1.0.3.dist-info/top_level.txt
iwin_cli-1.0.3.dist-info/RECORD
