Metadata-Version: 2.1
Name: iwin-cli
Version: 1.0.3
Summary: iwin commandline tool
Home-page: https://iwin2.3thinking.cn
Author: Learner Chen
Author-email: learner.chen@icloud.com
License: NO-DISTRIBUTION
Classifier: Programming Language :: Python
Classifier: Programming Language :: Python :: 3.7
Requires-Dist: et-xmlfile
Requires-Dist: numpy
Requires-Dist: openpyxl
Requires-Dist: pandas
Requires-Dist: XlsxWriter
Requires-Dist: Pillow
Requires-Dist: colorama
